{
    "source": "Зрителям показывают рекламу единожды перед началом трансляции.",
    "row": 61,
    "question": "Вы показываете рекламу на трансляциях?",
    "answer": "Зрителям показывают рекламу единожды перед началом трансляции.",
    "classifier_1": "ТРАНСЛЯЦИЯ",
    "classifier_2": "Просмотр трансляции",
    "questions": {
        "user_queries": [
            {
                "query": "Привет, идет ли реклама во время трансляции?"
            },
            {
                "query": "Здравствуйте! Показывается ли реклама при просмотре трансляций?"
            },
            {
                "query": "А рекламу показывают до или во время стримов?"
            },
            {
                "query": "Реклама показывается в трансляциях?"
            },
            {
                "query": "Скажите, реклама идет перед трансляцией или в процессе?"
            },
            {
                "query": "Перед трансляцией показывают рекламу или нет?"
            },
            {
                "query": "Есть ли реклама на стримах в вашем приложении?"
            },
            {
                "query": "Показывают ли зрителям рекламу во время трансляций?"
            },
            {
                "query": "Рекламу крутят перед трансляциями?"
            },
            {
                "query": "Как часто зрители видят рекламу на трансляциях?"
            }
        ]
    },
    "split_answer": "Зрителям показывают рекламу единожды перед началом трансляции."
}