{
    "source": "Если с момента удаления аккаунта прошло менее 30 дней, вы можете авторизоваться на RUTUBE привычным способом, и ваш аккаунт автоматически восстановится. Если авторизоваться не удалось и аккаунт удален не более 180 дней назад, напишите нам на help@rutube.ru – поможем с восстановлением.",
    "row": 919,
    "question": "Я удалил свой аккаунт, а теперь хочу восстановить его. Как это сделать?",
    "answer": "Если с момента удаления аккаунта прошло менее 30 дней, вы можете авторизоваться на RUTUBE привычным способом, и ваш аккаунт автоматически восстановится. Если авторизоваться не удалось и аккаунт удален не более 180 дней назад, напишите нам на help@rutube.ru – поможем с восстановлением.",
    "classifier_1": "УПРАВЛЕНИЕ АККАУНТОМ",
    "classifier_2": "Регистрация/Авторизация",
    "questions": {
        "user_queries": [
            {
                "query": "Как восстановить аккаунт, если я его удалил?"
            },
            {
                "query": "Удалил свой аккаунт RUTUBE. Можно ли его вернуть?"
            },
            {
                "query": "Привет, как мне вернуть удалённый акаунт? Прошло где-то 2 недели"
            },
            {
                "query": "Здравствуйте! Я случайно удалил аккаунт. Как его восстановить?"
            },
            {
                "query": "Удалил аккаунт и хочу его вернуть, что делать?"
            },
            {
                "query": "Помогите восстановить аккаунт, который я удалил месяц назад"
            },
            {
                "query": "Я удалил свой аккаунт, но хочу его вернуть. Как это можно сделать?"
            },
            {
                "query": "Удалил учетную запись, как её восстановить?"
            },
            {
                "query": "Как мне вернуть свой удалённый аккаунт на RUTUBE? Прошло меньше 30 дней"
            },
            {
                "query": "Я удалил свой аккаунт, а теперь хочу восстановить его. Как это сделать?"
            }
        ]
    },
    "split_answer": "Если с момента удаления аккаунта прошло менее 30 дней, вы можете авторизоваться на RUTUBE привычным способом, и ваш аккаунт автоматически восстановится. Если авторизоваться не удалось и аккаунт удален не более 180 дней назад, напишите нам на help@rutube.ru – поможем с восстановлением."
}