{
    "source": "Рассмотрение заявки на верификацию длится до 10 рабочих дней.",
    "row": 716,
    "question": "Сколько вы будете проверять мою заявку на верификацию?",
    "answer": "Рассмотрение заявки на верификацию длится до 10 рабочих дней.",
    "classifier_1": "УПРАВЛЕНИЕ АККАУНТОМ",
    "classifier_2": "Верификация",
    "questions": {
        "user_queries": [
            {
                "query": "Привет! А сколько времени займёт проверка моей заявки на верификацию?"
            },
            {
                "query": "Подскажите, сколько дней будет проверяться моя заявка на верификацию?"
            },
            {
                "query": "Сколько по времени идёт процесс верификации моей заявки?"
            },
            {
                "query": "Как долго длится проверка заявки на верификацию?"
            },
            {
                "query": "Сколько времени занимает верификация заявки?"
            },
            {
                "query": "Добрый день, сколько ждать проверку моей заявки на верификацию?"
            },
            {
                "query": "Заявка на верификацию проверяется 10 рабочих дней?"
            },
            {
                "query": "Сколько времени займёт верификация моей заявки?"
            },
            {
                "query": "Когда я могу ожидать завершение проверки моей заявки на верификацию?"
            },
            {
                "query": "Как быстро будет проверена моя заявка на верификацию?"
            }
        ]
    },
    "split_answer": "Рассмотрение заявки на верификацию длится до 10 рабочих дней."
}