{
    "source": "Да, авторизоваться в приложении можно по номеру телефона или электронной почте, которые указаны в профиле.",
    "row": 441,
    "question": "Могу зайти в студию приложение на андроид по номеру телефона? Также как на сайте или как надо то ничего не понятно сделайте уже яснее",
    "answer": "Да, авторизоваться в приложении можно по номеру телефона или электронной почте, которые указаны в профиле.",
    "classifier_1": "УПРАВЛЕНИЕ АККАУНТОМ",
    "classifier_2": "Регистрация/Авторизация",
    "questions": {
        "user_queries": [
            {
                "query": "Можно ли войти в приложение студии на андроиде используя номер телефона?"
            },
            {
                "query": "Привет, а как зайти в приложение студия на андроид через телефон?"
            },
            {
                "query": "Могу ли я авторизоваться в приложении на андроид по номеру телефона, как на сайте?"
            },
            {
                "query": "Как войти в студию на андроиде по номеру телефона? Не могу разобраться."
            },
            {
                "query": "Эй, можно войти в приложение по телефону? Ничего не понятно."
            },
            {
                "query": "Приложение студии на андроид: как войти по номеру телефона?"
            },
            {
                "query": "Здравствуйте! Могу ли я войти в приложение студии на андроид по номеру телефона?"
            },
            {
                "query": "Как авторизироваться в приложении студии на андроид через номер телефона?"
            },
            {
                "query": "Вопрос: можно ли войти в приложение на андроиде по номеру телефона?"
            },
            {
                "query": "Как зайти в приложение студии на андроид, используя телефонный номер?"
            }
        ]
    },
    "split_answer": "Да, авторизоваться в приложении можно по номеру телефона или электронной почте, которые указаны в профиле."
}