{
    "source": "Такая функция еще не реализована, следите за нашими обновлениями. Мы рекомендуем выдавать доступы только тем пользователям, которым вы полностью доверяете.",
    "row": 966,
    "question": "как мне посмотреть что делал мой администратор на моем канале?",
    "answer": "Такая функция еще не реализована, следите за нашими обновлениями. Мы рекомендуем выдавать доступы только тем пользователям, которым вы полностью доверяете.",
    "classifier_1": "ПРЕДЛОЖЕНИЯ",
    "classifier_2": "Студия RUTUBE",
    "questions": {
        "user_queries": [
            {
                "query": "Здравствуйте, как узнать, что делал мой админ на моем канале?"
            },
            {
                "query": "Как отследить действия администратора на канале?"
            },
            {
                "query": "Привет! Как я могу проверить активность моего администратора на канале?"
            },
            {
                "query": "Можно ли увидеть, что делает администратор на моем канале?"
            },
            {
                "query": "Как мониторить действия админа на моем канале?"
            },
            {
                "query": "Каким образом я могу узнать, что делал мой администратор на моем канале?"
            },
            {
                "query": "Где найти информацию о действиях моего администратора на канале?"
            },
            {
                "query": "Как посмотреть, какие действия выполнял администратор на канале?"
            },
            {
                "query": "Есть ли возможность увидеть, что делает администратор на моем канале?"
            },
            {
                "query": "Как можно проверить, что сделал администратор на моем канале?"
            }
        ]
    },
    "split_answer": "Такая функция еще не реализована, следите за нашими обновлениями. Мы рекомендуем выдавать доступы только тем пользователям, которым вы полностью доверяете."
}