{
    "source": "Историю просмотра вы можете найти в разделе «Моё».",
    "row": 427,
    "question": "Куда сохраняется история, что я смотрел?",
    "answer": "Историю просмотра вы можете найти в разделе «Моё».",
    "classifier_1": "УПРАВЛЕНИЕ АККАУНТОМ",
    "classifier_2": "Персонализация",
    "questions": {
        "user_queries": [
            {
                "query": "Где я могу найти историю того, что я смотрел?"
            },
            {
                "query": "Куда сохраняется список просмотренных мной видео?"
            },
            {
                "query": "Как посмотреть мои прошлые просмотры?"
            },
            {
                "query": "Подскажите, где найти историю моих видео?"
            },
            {
                "query": "Здравствуйте. Где я могу найти историю просмотров в приложении?"
            },
            {
                "query": "В каком разделе можно увидеть, что я смотрел?"
            },
            {
                "query": "Куда сохраняется история просмотров?"
            },
            {
                "query": "Как найти раздел с историей просмотренных видео?"
            },
            {
                "query": "Где хранится информация о моих просмотрах?"
            },
            {
                "query": "Как мне посмотреть историю просмотров?"
            }
        ]
    },
    "split_answer": "Историю просмотра вы можете найти в разделе «Моё»."
}