{
    "source": "Приложение доступно для бесплатной загрузки через магазин приложений вашего ТВ.",
    "row": 619,
    "question": "Недавно купил смарт тв, откуда скачать ваше приложение можно?",
    "answer": "Приложение доступно для бесплатной загрузки через магазин приложений вашего ТВ.",
    "classifier_1": "ДОСТУП К RUTUBE",
    "classifier_2": "Приложение",
    "questions": {
        "user_queries": [
            {
                "query": "Привет, недавно взял смарт телевизор, где можно ваше приложение скачать?"
            },
            {
                "query": "Здравствуйте! Подскажите, откуда можно загрузить ваше приложение на смарт ТВ?"
            },
            {
                "query": "Купил новый смарт-телевизор, где скачать ваше приложение?"
            },
            {
                "query": "Где найти ваше приложение для смарт тв?"
            },
            {
                "query": "Добрый день, подскажите, где можно скачать приложение для моего нового смарт ТВ?"
            },
            {
                "query": "Как загрузить ваше приложение на смарт ТВ?"
            },
            {
                "query": "Откуда скачать приложение для смарт-телевизора?"
            },
            {
                "query": "На каком сайте можно скачать ваше приложение для смарт тв?"
            },
            {
                "query": "Здравствуйте! Советуйте, откуда скачать ваше приложение для смарт телевизора?"
            },
            {
                "query": "Купил смарт ТВ, где качнуть ваше приложение?"
            }
        ]
    },
    "split_answer": "Приложение доступно для бесплатной загрузки через магазин приложений вашего ТВ."
}