{
    "source": "Здравствуйте, пожалуйста, направьте нам на partners@rutube.ru убедительные факты, которые помогли бы нам удостовериться, что вы можете претендовать на статус официального.",
    "row": 617,
    "question": "Не согласен с тем, что я не дали статус официального канала",
    "answer": "Здравствуйте, пожалуйста, направьте нам на partners@rutube.ru убедительные факты, которые помогли бы нам удостовериться, что вы можете претендовать на статус официального.",
    "classifier_1": "УПРАВЛЕНИЕ АККАУНТОМ",
    "classifier_2": "Верификация",
    "questions": {
        "user_queries": [
            {
                "query": "Почему мне не дали статус официального канала?"
            },
            {
                "query": "Добрый день! Не согласен с решением по статусу официального канала. Куда отправить доказательства?"
            },
            {
                "query": "Как получить статус официального канала, если я считаю, что заслуживаю его?"
            },
            {
                "query": "Почему я не получил статус официального? Куда можно отправить информацию, чтобы пересмотрели?"
            },
            {
                "query": "Меня не признали официальным каналом. Куда писать?"
            },
            {
                "query": "Где я могу предоставить доказательства, что достоин статуса официального канала?"
            },
            {
                "query": "Не понимаю, почему мой канал не признали официальным. Куда отправить аргументы?"
            },
            {
                "query": "На какой email направить факты для получения статуса официального канала?"
            },
            {
                "query": "Привет! Не дали статус официального канала. Куда отправить доказательства?"
            },
            {
                "query": "Как доказать, что мой канал должен быть официальным?"
            }
        ]
    },
    "split_answer": "Здравствуйте, пожалуйста, направьте нам на partners@rutube.ru убедительные факты, которые помогли бы нам удостовериться, что вы можете претендовать на статус официального."
}