{
    "source": "Вероятнее всего, у вас стоит блокировщик рекламы. Отключите его или добавьте RUTUBE в исключения в настройках блокировщика.",
    "row": 679,
    "question": "Почнм нельзя смотреть видео в хорошем качестве?",
    "answer": "Вероятнее всего, у вас стоит блокировщик рекламы. Отключите его или добавьте RUTUBE в исключения в настройках блокировщика.",
    "classifier_1": "ВИДЕО",
    "classifier_2": "Воспроизведение видео",
    "questions": {
        "user_queries": [
            {
                "query": "Почему у меня не получается смотреть видео в высоком качестве?"
            },
            {
                "query": "Здраствуйте, подскажите, почему видео не воспроизводится в хорошем качестве?"
            },
            {
                "query": "Как сделать так, чтобы видео на RUTUBE было в HD качестве?"
            },
            {
                "query": "Видео на сайте не показывает в высоком качестве, что делать?"
            },
            {
                "query": "Проблемы с качеством видео, почему не могу смотреть в хорошем качестве?"
            },
            {
                "query": "Почему видео на Рутубе не идет в хорошем качестве?"
            },
            {
                "query": "Не могу смотреть видео в высоком качестве. Что может быть причиной?"
            },
            {
                "query": "Видео на RUTUBE не загружается в хорошем качестве. Что делать?"
            },
            {
                "query": "Как исправить, если видео не идет в хорошем качестве?"
            },
            {
                "query": "Почему нельзя смотреть видео в хорошем качестве?"
            }
        ]
    },
    "split_answer": "Вероятнее всего, у вас стоит блокировщик рекламы. Отключите его или добавьте RUTUBE в исключения в настройках блокировщика."
}